joy/__init__.py
joy-0.0.1.dist-info/METADATA
joy-0.0.1.dist-info/WHEEL
joy-0.0.1.dist-info/top_level.txt
joy-0.0.1.dist-info/RECORD
