Metadata-Version: 1.1
Name: joy
Version: 0.0.1
Summary: joy library for AI research
Home-page: UNKNOWN
Author: Lab
Author-email: UNKNOWN
License: MIT
Platform: UNKNOWN
Classifier: Development Status :: 4 - Beta
Classifier: Programming Language :: Python :: 3
